spdconv/SPDConv.py
spdconv/__init__.py
spdconv-0.1.0.dist-info/LICENSE
spdconv-0.1.0.dist-info/METADATA
spdconv-0.1.0.dist-info/WHEEL
spdconv-0.1.0.dist-info/top_level.txt
spdconv-0.1.0.dist-info/RECORD
